{"minified":"composer/2.0","packages":{"shrikeh/teapot":[{"name":"shrikeh/teapot","description":"PHP HTTP Response Status library","keywords":["http"],"homepage":"https://shrikeh.github.io/teapot/","version":"3.0.0","version_normalized":"3.0.0.0","license":["MIT"],"authors":[{"name":"Barney Hanlon","email":"barney@shrikeh.net"},{"name":"Andreas Möller","email":"am@localheinz.com"}],"source":{"url":"https://github.com/shrikeh/teapot.git","type":"git","reference":"ff9b86b698696e701dcced00c7e225be7be880dd"},"dist":{"url":"https://api.github.com/repos/shrikeh/teapot/zipball/ff9b86b698696e701dcced00c7e225be7be880dd","type":"zip","shasum":"","reference":"ff9b86b698696e701dcced00c7e225be7be880dd"},"type":"library","support":{"issues":"https://github.com/shrikeh/teapot/issues","source":"https://github.com/shrikeh/teapot/tree/3.0.0"},"funding":[],"time":"2023-09-08T11:52:13+00:00","autoload":{"psr-4":{"Teapot\\":"src"}},"require":{"php":">=8.0","psr/http-message":"^1.1 || ^2.0","teapot/status-code":"^2.1"},"require-dev":{"ergebnis/php-cs-fixer-config":"^5.9.2","phpspec/phpspec":"^7.4","vimeo/psalm":"^5.14.1"}},{"version":"v2.3.1","version_normalized":"2.3.1.0","source":{"url":"https://github.com/shrikeh/teapot.git","type":"git","reference":"2fea5720963f22eedb920ee65b9d643bfa3e8daf"},"dist":{"url":"https://api.github.com/repos/shrikeh/teapot/zipball/2fea5720963f22eedb920ee65b9d643bfa3e8daf","type":"zip","shasum":"","reference":"2fea5720963f22eedb920ee65b9d643bfa3e8daf"},"support":{"issues":"https://github.com/shrikeh/teapot/issues","source":"https://github.com/shrikeh/teapot/tree/master"},"time":"2017-09-01T13:56:48+00:00","require":{"php":">=5.5","psr/http-message":"^1.0","teapot/status-code":"^1.0"},"require-dev":{"phpspec/phpspec":"~3.0.0","bossa/phpspec2-expect":"^2.0","behat/behat":"^3.2","squizlabs/php_codesniffer":"^2.7","escapestudios/symfony2-coding-standard":"^2.9"},"funding":"__unset"},{"version":"v2.3.0","version_normalized":"2.3.0.0","source":{"url":"https://github.com/shrikeh/teapot.git","type":"git","reference":"a28142273cbd84813355c461a1be3e011c43d6be"},"dist":{"url":"https://api.github.com/repos/shrikeh/teapot/zipball/a28142273cbd84813355c461a1be3e011c43d6be","type":"zip","shasum":"","reference":"a28142273cbd84813355c461a1be3e011c43d6be"},"support":{"issues":"https://github.com/shrikeh/teapot/issues","source":"https://github.com/shrikeh/teapot/tree/develop"},"time":"2017-02-19T15:30:04+00:00"},{"version":"v2.2.1","version_normalized":"2.2.1.0","authors":[{"name":"Barney Hanlon","email":"barney@shrikeh.net"}],"source":{"url":"https://github.com/shrikeh/teapot.git","type":"git","reference":"0f1c78ff18b6a1986b5bb85ccf593ef00634e006"},"dist":{"url":"https://api.github.com/repos/shrikeh/teapot/zipball/0f1c78ff18b6a1986b5bb85ccf593ef00634e006","type":"zip","shasum":"","reference":"0f1c78ff18b6a1986b5bb85ccf593ef00634e006"},"support":{"issues":"https://github.com/shrikeh/teapot/issues","source":"https://github.com/shrikeh/teapot/tree/master"},"time":"2017-01-03T13:51:21+00:00","require":{"php":">=5.3","psr/http-message":"^1.0","teapot/status-code":"^1.0"},"require-dev":{"squizlabs/php_codesniffer":"^2.3","phpspec/phpspec":"^3.1","escapestudios/symfony2-coding-standard":"~2.0"},"suggest":{"fabpot/php-cs-fixer":"^1.11 - For easy CS fixing"}},{"version":"v2.2","version_normalized":"2.2.0.0","source":{"url":"https://github.com/shrikeh/teapot.git","type":"git","reference":"796d3e558a2c0e41dc3d0ff38303e4131ce92bda"},"dist":{"url":"https://api.github.com/repos/shrikeh/teapot/zipball/796d3e558a2c0e41dc3d0ff38303e4131ce92bda","type":"zip","shasum":"","reference":"796d3e558a2c0e41dc3d0ff38303e4131ce92bda"},"time":"2016-11-16T09:07:20+00:00","require-dev":{"squizlabs/php_codesniffer":"^2.3","escapestudios/symfony2-coding-standard":"~2.0","phpspec/phpspec":"^2.5"}},{"version":"v2.1","version_normalized":"2.1.0.0","source":{"url":"https://github.com/shrikeh/teapot.git","type":"git","reference":"50c6ba96fea23588d9bf23815118ef7b7d5fe53e"},"dist":{"url":"https://api.github.com/repos/shrikeh/teapot/zipball/50c6ba96fea23588d9bf23815118ef7b7d5fe53e","type":"zip","shasum":"","reference":"50c6ba96fea23588d9bf23815118ef7b7d5fe53e"},"time":"2016-06-27T11:59:47+00:00","require":{"php":">=5.3","psr/http-message":"^1.0"}},{"version":"v2.0","version_normalized":"2.0.0.0","source":{"url":"https://github.com/shrikeh/teapot.git","type":"git","reference":"1495e953780fe3eb9c42b34a41309391eb05f9ec"},"dist":{"url":"https://api.github.com/repos/shrikeh/teapot/zipball/1495e953780fe3eb9c42b34a41309391eb05f9ec","type":"zip","shasum":"","reference":"1495e953780fe3eb9c42b34a41309391eb05f9ec"},"time":"2016-04-22T12:20:57+00:00","require":{"php":">=5.3","nette/reflection":"^2.3","psr/http-message":"^1.0"}},{"homepage":"http://shrikeh.github.com/teapot","version":"v1.0.2","version_normalized":"1.0.2.0","source":{"url":"https://github.com/shrikeh/teapot.git","type":"git","reference":"879ad8e197b75d0a34afb92e0ec70b75fd5cf171"},"dist":{"url":"https://api.github.com/repos/shrikeh/teapot/zipball/879ad8e197b75d0a34afb92e0ec70b75fd5cf171","type":"zip","shasum":"","reference":"879ad8e197b75d0a34afb92e0ec70b75fd5cf171"},"time":"2015-08-17T09:36:20+00:00","autoload":{"psr-0":{"Teapot":"src"}},"require":{"php":">=5.3.3","squizlabs/php_codesniffer":"^2.3"},"require-dev":"__unset","suggest":"__unset"},{"version":"1.0.1","version_normalized":"1.0.1.0","source":{"url":"https://github.com/shrikeh/teapot.git","type":"git","reference":"ddfed900549b8f510a55a882864cc75f8246b36c"},"dist":{"url":"https://api.github.com/repos/shrikeh/teapot/zipball/ddfed900549b8f510a55a882864cc75f8246b36c","type":"zip","shasum":"","reference":"ddfed900549b8f510a55a882864cc75f8246b36c"},"support":{"issues":"https://github.com/shrikeh/teapot/issues","source":"https://github.com/shrikeh/teapot/tree/1.0.1"},"time":"2014-11-01T11:52:00+00:00","require":{"php":">=5.3.3"},"require-dev":{"phploc/phploc":">=1.7.4","pdepend/pdepend":"1.1.0","sebastian/phpcpd":"2.0.*@dev","mayflower/php-codebrowser":"~1.1","phpmd/phpmd":">=1.4.0","squizlabs/php_codesniffer":"1.*","phpdocumentor/phpdocumentor":"2.*"}},{"version":"1.0.0","version_normalized":"1.0.0.0","source":{"url":"https://github.com/shrikeh/teapot.git","type":"git","reference":"ae9c9df113e54ca243d4e5a6291bc2c37e528a30"},"dist":{"url":"https://api.github.com/repos/shrikeh/teapot/zipball/ae9c9df113e54ca243d4e5a6291bc2c37e528a30","type":"zip","shasum":"","reference":"ae9c9df113e54ca243d4e5a6291bc2c37e528a30"},"support":{"issues":"https://github.com/shrikeh/teapot/issues","source":"https://github.com/shrikeh/teapot/tree/master"},"time":"2014-03-03T20:03:36+00:00","autoload":{"psr-0":{"Teapot":"lib"}}},{"version":"0.2","version_normalized":"0.2.0.0","source":{"url":"https://github.com/shrikeh/teapot.git","type":"git","reference":"2ef6f30a6cd228de4d7da249b837d05b12df4b01"},"dist":{"url":"https://api.github.com/repos/shrikeh/teapot/zipball/2ef6f30a6cd228de4d7da249b837d05b12df4b01","type":"zip","shasum":"","reference":"2ef6f30a6cd228de4d7da249b837d05b12df4b01"},"time":"2013-04-05T00:27:08+00:00","require-dev":{"phpunit/phpunit":"3.7.*","phploc/phploc":">=1.7.4","pdepend/pdepend":"*","shrink/phpcpd":"dev-master","zerkalica/php-code-browser":"dev-master","phpmd/phpmd":">=1.4.0","squizlabs/php_codesniffer":"1.*","phpdocumentor/phpdocumentor":"2.*"}},{"version":"0.1","version_normalized":"0.1.0.0","source":{"url":"https://github.com/shrikeh/teapot.git","type":"git","reference":"3c21d2b9a3d375b7019bed8ba2787357d8d83bc6"},"dist":{"url":"https://api.github.com/repos/shrikeh/teapot/zipball/3c21d2b9a3d375b7019bed8ba2787357d8d83bc6","type":"zip","shasum":"","reference":"3c21d2b9a3d375b7019bed8ba2787357d8d83bc6"},"time":"2013-04-02T10:37:32+00:00","require-dev":"__unset"}]},"security-advisories":[],"last-modified":"Mon, 07 Oct 2024 12:25:40 GMT"}